jupyter_ai_dalle/__init__.py
jupyter_ai_dalle/_version.py
jupyter_ai_dalle/engine.py
jupyter_ai_dalle/tasks.py
jupyter_ai_dalle/tests/__init__.py
jupyter_ai_dalle-0.5.0.data/data/share/jupyter/labextensions/@jupyter-ai/dalle/package.json
jupyter_ai_dalle-0.5.0.data/data/share/jupyter/labextensions/@jupyter-ai/dalle/static/568.360c80aecf15fb74bd5d.js
jupyter_ai_dalle-0.5.0.data/data/share/jupyter/labextensions/@jupyter-ai/dalle/static/643.9e0e6dc147127c5f5b07.js
jupyter_ai_dalle-0.5.0.data/data/share/jupyter/labextensions/@jupyter-ai/dalle/static/remoteEntry.5f267942fa0b6ca3ba8e.js
jupyter_ai_dalle-0.5.0.data/data/share/jupyter/labextensions/@jupyter-ai/dalle/static/style.js
jupyter_ai_dalle-0.5.0.data/data/share/jupyter/labextensions/@jupyter-ai/dalle/static/third-party-licenses.json
jupyter_ai_dalle-0.5.0.data/data/share/jupyter/labextensions/@jupyter-ai/dalle/install.json
jupyter_ai_dalle-0.5.0.dist-info/METADATA
jupyter_ai_dalle-0.5.0.dist-info/WHEEL
jupyter_ai_dalle-0.5.0.dist-info/entry_points.txt
jupyter_ai_dalle-0.5.0.dist-info/licenses/LICENSE
jupyter_ai_dalle-0.5.0.dist-info/RECORD
